pytest_goldie/plugin.py
pytest_goldie-0.1.5.dist-info/LICENSE
pytest_goldie-0.1.5.dist-info/METADATA
pytest_goldie-0.1.5.dist-info/WHEEL
pytest_goldie-0.1.5.dist-info/entry_points.txt
pytest_goldie-0.1.5.dist-info/top_level.txt
pytest_goldie-0.1.5.dist-info/RECORD
